Workbook

Sheet O-Feature-Inventory
C1: =MID(CELL("filename",A1),FIND("[",CELL("filename",A1))+1,FIND("]",CELL("filename",A1))-FIND("[",CELL("filename",A1))-1)&" - "&MID(CELL("filename",A1),FIND("]",CELL("filename",A1))+1,255)
A3: =IF('Z-Validation-Checks'!D8="OK","OK","ERROR") | C3: O-Feature-Inventory — Master View
C7: # | D7: Feature_ID | E7: Category | F7: Feature_Name | G7: Phase | H7: Priority | I7: Effort | J7: Status | K7: Owner
C8: 1 | D8: ='I-Features'!C8 | E8: ='I-Features'!D8 | F8: ='I-Features'!E8 | G8: ='I-Features'!H8 | H8: ='I-Features'!I8 | I8: ='I-Features'!J8 | J8: ='I-Features'!M8 | K8: ='I-Features'!L8
C9: 2 | D9: ='I-Features'!C9 | E9: ='I-Features'!D9 | F9: ='I-Features'!E9 | G9: ='I-Features'!H9 | H9: ='I-Features'!I9 | I9: ='I-Features'!J9 | J9: ='I-Features'!M9 | K9: ='I-Features'!L9
C10: 3 | D10: ='I-Features'!C10 | E10: ='I-Features'!D10 | F10: ='I-Features'!E10 | G10: ='I-Features'!H10 | H10: ='I-Features'!I10 | I10: ='I-Features'!J10 | J10: ='I-Features'!M10 | K10: ='I-Features'!L10
C11: 4 | D11: ='I-Features'!C11 | E11: ='I-Features'!D11 | F11: ='I-Features'!E11 | G11: ='I-Features'!H11 | H11: ='I-Features'!I11 | I11: ='I-Features'!J11 | J11: ='I-Features'!M11 | K11: ='I-Features'!L11
C12: 5 | D12: ='I-Features'!C12 | E12: ='I-Features'!D12 | F12: ='I-Features'!E12 | G12: ='I-Features'!H12 | H12: ='I-Features'!I12 | I12: ='I-Features'!J12 | J12: ='I-Features'!M12 | K12: ='I-Features'!L12
C13: 6 | D13: ='I-Features'!C13 | E13: ='I-Features'!D13 | F13: ='I-Features'!E13 | G13: ='I-Features'!H13 | H13: ='I-Features'!I13 | I13: ='I-Features'!J13 | J13: ='I-Features'!M13 | K13: ='I-Features'!L13
C14: 7 | D14: ='I-Features'!C14 | E14: ='I-Features'!D14 | F14: ='I-Features'!E14 | G14: ='I-Features'!H14 | H14: ='I-Features'!I14 | I14: ='I-Features'!J14 | J14: ='I-Features'!M14 | K14: ='I-Features'!L14
C15: 8 | D15: ='I-Features'!C15 | E15: ='I-Features'!D15 | F15: ='I-Features'!E15 | G15: ='I-Features'!H15 | H15: ='I-Features'!I15 | I15: ='I-Features'!J15 | J15: ='I-Features'!M15 | K15: ='I-Features'!L15
C16: 9 | D16: ='I-Features'!C16 | E16: ='I-Features'!D16 | F16: ='I-Features'!E16 | G16: ='I-Features'!H16 | H16: ='I-Features'!I16 | I16: ='I-Features'!J16 | J16: ='I-Features'!M16 | K16: ='I-Features'!L16
C17: 10 | D17: ='I-Features'!C17 | E17: ='I-Features'!D17 | F17: ='I-Features'!E17 | G17: ='I-Features'!H17 | H17: ='I-Features'!I17 | I17: ='I-Features'!J17 | J17: ='I-Features'!M17 | K17: ='I-Features'!L17
C18: 11 | D18: ='I-Features'!C18 | E18: ='I-Features'!D18 | F18: ='I-Features'!E18 | G18: ='I-Features'!H18 | H18: ='I-Features'!I18 | I18: ='I-Features'!J18 | J18: ='I-Features'!M18 | K18: ='I-Features'!L18
C19: 12 | D19: ='I-Features'!C19 | E19: ='I-Features'!D19 | F19: ='I-Features'!E19 | G19: ='I-Features'!H19 | H19: ='I-Features'!I19 | I19: ='I-Features'!J19 | J19: ='I-Features'!M19 | K19: ='I-Features'!L19
... C76: 69 | D76: ='I-Features'!C76 | E76: ='I-Features'!D76 | F76: ='I-Features'!E76 | G76: ='I-Features'!H76 | H76: ='I-Features'!I76 | I76: ='I-Features'!J76 | J76: ='I-Features'!M76 | K76: ='I-Features'!L76

Sheet O-Phase-Summary
C1: =MID(CELL("filename",A1),FIND("[",CELL("filename",A1))+1,FIND("]",CELL("filename",A1))-FIND("[",CELL("filename",A1))-1)&" - "&MID(CELL("filename",A1),FIND("]",CELL("filename",A1))+1,255)
A3: =IF(TRUE,"OK","ERROR") | C3: O-Phase-Summary — Rollup by Phase
C7: Phase | D7: Total | E7: Not Started | F7: In Progress | G7: In Review | H7: Done | I7: Deferred | J7: % Complete | K7: Effort Points
C8: MVP | D8: =COUNTIF('I-Features'!$H$8:$H$76,C8) | E8: =COUNTIFS('I-Features'!$H$8:$H$76,C8,'I-Features'!$M$8:$M$76,"Not Started") | F8: =COUNTIFS('I-Features'!$H$8:$H$76,C8,'I-Features'!$M$8:$M$76,"In Progress") | G8: =COUNTIFS('I-Features'!$H$8:$H$76,C8,'I-Features'!$M$8:$M$76,"In Review") | H8: =COUNTIFS('I-Features'!$H$8:$H$76,C8,'I-Features'!$M$8:$M$76,"Done") | I8: =COUNTIFS('I-Features'!$H$8:$H$76,C8,'I-Features'!$M$8:$M$76,"Deferred") | J8: =IFERROR(H8/D8,"-") | K8: =SUMIF('I-Features'!$H$8:$H$76,C8,'C-Feature-Calcs'!$F$8:$F$76)
C9: Phase 2 | D9: =COUNTIF('I-Features'!$H$8:$H$76,C9) | E9: =COUNTIFS('I-Features'!$H$8:$H$76,C9,'I-Features'!$M$8:$M$76,"Not Started") | F9: =COUNTIFS('I-Features'!$H$8:$H$76,C9,'I-Features'!$M$8:$M$76,"In Progress") | G9: =COUNTIFS('I-Features'!$H$8:$H$76,C9,'I-Features'!$M$8:$M$76,"In Review") | H9: =COUNTIFS('I-Features'!$H$8:$H$76,C9,'I-Features'!$M$8:$M$76,"Done") | I9: =COUNTIFS('I-Features'!$H$8:$H$76,C9,'I-Features'!$M$8:$M$76,"Deferred") | J9: =IFERROR(H9/D9,"-") | K9: =SUMIF('I-Features'!$H$8:$H$76,C9,'C-Feature-Calcs'!$F$8:$F$76)
C10: Phase 3 | D10: =COUNTIF('I-Features'!$H$8:$H$76,C10) | E10: =COUNTIFS('I-Features'!$H$8:$H$76,C10,'I-Features'!$M$8:$M$76,"Not Started") | F10: =COUNTIFS('I-Features'!$H$8:$H$76,C10,'I-Features'!$M$8:$M$76,"In Progress") | G10: =COUNTIFS('I-Features'!$H$8:$H$76,C10,'I-Features'!$M$8:$M$76,"In Review") | H10: =COUNTIFS('I-Features'!$H$8:$H$76,C10,'I-Features'!$M$8:$M$76,"Done") | I10: =COUNTIFS('I-Features'!$H$8:$H$76,C10,'I-Features'!$M$8:$M$76,"Deferred") | J10: =IFERROR(H10/D10,"-") | K10: =SUMIF('I-Features'!$H$8:$H$76,C10,'C-Feature-Calcs'!$F$8:$F$76)
C11: Phase 4 | D11: =COUNTIF('I-Features'!$H$8:$H$76,C11) | E11: =COUNTIFS('I-Features'!$H$8:$H$76,C11,'I-Features'!$M$8:$M$76,"Not Started") | F11: =COUNTIFS('I-Features'!$H$8:$H$76,C11,'I-Features'!$M$8:$M$76,"In Progress") | G11: =COUNTIFS('I-Features'!$H$8:$H$76,C11,'I-Features'!$M$8:$M$76,"In Review") | H11: =COUNTIFS('I-Features'!$H$8:$H$76,C11,'I-Features'!$M$8:$M$76,"Done") | I11: =COUNTIFS('I-Features'!$H$8:$H$76,C11,'I-Features'!$M$8:$M$76,"Deferred") | J11: =IFERROR(H11/D11,"-") | K11: =SUMIF('I-Features'!$H$8:$H$76,C11,'C-Feature-Calcs'!$F$8:$F$76)
C12: TOTAL | D12: =SUM(D8:D11) | E12: =SUM(E8:E11) | F12: =SUM(F8:F11) | G12: =SUM(G8:G11) | H12: =SUM(H8:H11) | I12: =SUM(I8:I11) | J12: =IFERROR(H12/D12,"-") | K12: =SUM(K8:K11)

Sheet C-Feature-Calcs
C1: =MID(CELL("filename",A1),FIND("[",CELL("filename",A1))+1,FIND("]",CELL("filename",A1))-FIND("[",CELL("filename",A1))-1)&" - "&MID(CELL("filename",A1),FIND("]",CELL("filename",A1))+1,255)
A3: =IF(TRUE,"OK","ERROR") | C3: C-Feature-Calcs — Derived Metrics
C7: Feature_ID | D7: Phase | E7: Effort | F7: Effort_Pts | G7: Status | H7: Is_Done | I7: Is_In_Progress
C8: ='I-Features'!C8 | D8: ='I-Features'!H8 | E8: ='I-Features'!J8 | F8: =IFERROR(VLOOKUP(E8,'A-Specific'!$F$8:$G$11,2,FALSE),0) | G8: ='I-Features'!M8 | H8: =IF(G8="Done",1,0) | I8: =IF(G8="In Progress",1,0)
C9: ='I-Features'!C9 | D9: ='I-Features'!H9 | E9: ='I-Features'!J9 | F9: =IFERROR(VLOOKUP(E9,'A-Specific'!$F$8:$G$11,2,FALSE),0) | G9: ='I-Features'!M9 | H9: =IF(G9="Done",1,0) | I9: =IF(G9="In Progress",1,0)
C10: ='I-Features'!C10 | D10: ='I-Features'!H10 | E10: ='I-Features'!J10 | F10: =IFERROR(VLOOKUP(E10,'A-Specific'!$F$8:$G$11,2,FALSE),0) | G10: ='I-Features'!M10 | H10: =IF(G10="Done",1,0) | I10: =IF(G10="In Progress",1,0)
C11: ='I-Features'!C11 | D11: ='I-Features'!H11 | E11: ='I-Features'!J11 | F11: =IFERROR(VLOOKUP(E11,'A-Specific'!$F$8:$G$11,2,FALSE),0) | G11: ='I-Features'!M11 | H11: =IF(G11="Done",1,0) | I11: =IF(G11="In Progress",1,0)
C12: ='I-Features'!C12 | D12: ='I-Features'!H12 | E12: ='I-Features'!J12 | F12: =IFERROR(VLOOKUP(E12,'A-Specific'!$F$8:$G$11,2,FALSE),0) | G12: ='I-Features'!M12 | H12: =IF(G12="Done",1,0) | I12: =IF(G12="In Progress",1,0)
C13: ='I-Features'!C13 | D13: ='I-Features'!H13 | E13: ='I-Features'!J13 | F13: =IFERROR(VLOOKUP(E13,'A-Specific'!$F$8:$G$11,2,FALSE),0) | G13: ='I-Features'!M13 | H13: =IF(G13="Done",1,0) | I13: =IF(G13="In Progress",1,0)
C14: ='I-Features'!C14 | D14: ='I-Features'!H14 | E14: ='I-Features'!J14 | F14: =IFERROR(VLOOKUP(E14,'A-Specific'!$F$8:$G$11,2,FALSE),0) | G14: ='I-Features'!M14 | H14: =IF(G14="Done",1,0) | I14: =IF(G14="In Progress",1,0)
C15: ='I-Features'!C15 | D15: ='I-Features'!H15 | E15: ='I-Features'!J15 | F15: =IFERROR(VLOOKUP(E15,'A-Specific'!$F$8:$G$11,2,FALSE),0) | G15: ='I-Features'!M15 | H15: =IF(G15="Done",1,0) | I15: =IF(G15="In Progress",1,0)
C16: ='I-Features'!C16 | D16: ='I-Features'!H16 | E16: ='I-Features'!J16 | F16: =IFERROR(VLOOKUP(E16,'A-Specific'!$F$8:$G$11,2,FALSE),0) | G16: ='I-Features'!M16 | H16: =IF(G16="Done",1,0) | I16: =IF(G16="In Progress",1,0)
C17: ='I-Features'!C17 | D17: ='I-Features'!H17 | E17: ='I-Features'!J17 | F17: =IFERROR(VLOOKUP(E17,'A-Specific'!$F$8:$G$11,2,FALSE),0) | G17: ='I-Features'!M17 | H17: =IF(G17="Done",1,0) | I17: =IF(G17="In Progress",1,0)
C18: ='I-Features'!C18 | D18: ='I-Features'!H18 | E18: ='I-Features'!J18 | F18: =IFERROR(VLOOKUP(E18,'A-Specific'!$F$8:$G$11,2,FALSE),0) | G18: ='I-Features'!M18 | H18: =IF(G18="Done",1,0) | I18: =IF(G18="In Progress",1,0)
C19: ='I-Features'!C19 | D19: ='I-Features'!H19 | E19: ='I-Features'!J19 | F19: =IFERROR(VLOOKUP(E19,'A-Specific'!$F$8:$G$11,2,FALSE),0) | G19: ='I-Features'!M19 | H19: =IF(G19="Done",1,0) | I19: =IF(G19="In Progress",1,0)
... C76: ='I-Features'!C76 | D76: ='I-Features'!H76 | E76: ='I-Features'!J76 | F76: =IFERROR(VLOOKUP(E76,'A-Specific'!$F$8:$G$11,2,FALSE),0) | G76: ='I-Features'!M76 | H76: =IF(G76="Done",1,0) | I76: =IF(G76="In Progress",1,0)

Sheet I-Features
C1: =MID(CELL("filename",A1),FIND("[",CELL("filename",A1))+1,FIND("]",CELL("filename",A1))-FIND("[",CELL("filename",A1))-1)&" - "&MID(CELL("filename",A1),FIND("]",CELL("filename",A1))+1,255)
A3: =IF(COUNTA(C8:C200)=69,"OK","ERROR") | C3: I-Features — Master Feature List (Inputs)
C7: Feature_ID | D7: Category | E7: Feature_Name | F7: User_Story | G7: Acceptance_Criteria | H7: Phase | I7: Priority | J7: Effort | K7: Dependencies | L7: Owner | M7: Status | N7: Notes
C8: AUTH-01 | D8: Auth | E8: Email magic-link login | F8: As a contractor I want to log in with just my email so I don't manage passwords. | G8: Magic link emailed; click signs in; link expires 15 min; rate limited per email/IP. | H8: MVP | I8: P0 | J8: M | L8: Brendan | M8: Not Started | N8: Auth.js + Resend
C9: AUTH-02 | D9: Auth | E9: Single-user workspace | F9: Each user gets an isolated workspace; data scoped by user_id. | G9: All queries filter by session userId; Playwright test proves no cross-user read. | H9: MVP | I9: P0 | J9: S | K9: AUTH-01 | L9: Brendan | M9: Not Started | N9: App-level scoping (RLS-lite); revisit when Phase 4 multi-user added.
C10: PROJ-01 | D10: Projects | E10: Create/edit project | F10: Create a project with name, status, dates. | G10: CRUD endpoints + list view + edit form; soft-delete supported. | H10: MVP | I10: P0 | J10: S | K10: AUTH-02 | L10: Brendan | M10: Not Started
C11: PROJ-02 | D11: Projects | E11: Client info per project | F11: Capture client name, phone, email per project. | G11: Stored on project; auto-populated into proposal PDF. | H11: MVP | I11: P0 | J11: S | K11: PROJ-01 | L11: Brendan | M11: Not Started
C12: PROJ-03 | D12: Projects | E12: Site address + photos | F12: Upload jobsite photos against a project for reference. | G12: Multi-upload, thumbnails, delete, EXIF preserved. | H12: MVP | I12: P0 | J12: M | K12: PROJ-01 | L12: Brendan | M12: Not Started | N12: Cloudflare R2 storage
C13: EST-01 | D13: Estimation | E13: Sections / rooms | F13: Group line items into rooms or scope sections. | G13: Add / rename / delete / reorder sections per project. | H13: MVP | I13: P0 | J13: S | K13: PROJ-01 | L13: Brendan | M13: Not Started
C14: EST-02 | D14: Estimation | E14: Line items | F14: Add line items with qty, unit, labor hrs, labor rate, material $, markup %. | G14: Inline-editable table; numeric validation; persists order_index. | H14: MVP | I14: P0 | J14: M | K14: EST-01 | L14: Brendan | M14: Not Started
C15: EST-03 | D15: Estimation | E15: Calc engine | F15: Pure calc: subtotals → labor burden → markup → overhead → profit → tax → total. | G15: Vitest unit tests for every edge case (zero qty, 100% markup, rounding). | H15: MVP | I15: P0 | J15: M | K15: EST-02 | L15: Brendan | M15: Not Started | N15: lib/calc.ts — single source of truth
C16: EST-04 | D16: Estimation | E16: Duplicate item / section | F16: One-click duplicate a line item or whole section. | G16: Works at item and section level; preserves order. | H16: MVP | I16: P0 | J16: S | K16: EST-02 | L16: Brendan | M16: Not Started
C17: EST-05 | D17: Estimation | E17: Reorder via drag | F17: Drag-reorder items and sections. | G17: Persists order_index to DB; works on touch. | H17: MVP | I17: P0 | J17: S | K17: EST-02 | L17: Brendan | M17: Not Started | N17: dnd-kit
C18: AI-01 | D18: AI Capture | E18: Voice → line items | F18: Record voice memo of jobsite walk-through; AI proposes line items. | G18: 60–120s clip → ≥1 mapped line item; flagged 'AI suggested' until confirmed. | H18: MVP | I18: P0 | J18: L | K18: EST-02, CAT-01 | L18: Brendan | M18: Not Started | N18: Whisper → GPT-4o structured output; golden-set regression test.
C19: AI-02 | D19: AI Capture | E19: Photo → line items | F19: Take 1–10 photos; AI suggests line items based on visible scope. | G19: Each suggestion shows confidence + source photo; user confirms each. | H19: MVP | I19: P0 | J19: L | K19: EST-02, CAT-01 | L19: Brendan | M19: Not Started | N19: GPT-4o vision
C20: AI-03 | D20: AI Capture | E20: Confirm UX (review-gate) | F20: Every AI item must be confirmed before included in a proposal. | G20: 'AI Suggested' badge until tap; cannot send proposal with unconfirmed items. | H20: MVP | I20: P0 | J20: M | K20: AI-01, AI-02 | L20: Brendan | M20: Not Started | N20: UX-critical for trust + liability
C21: AI-04 | D21: AI Capture | E21: Cost cap per project | F21: Prevent runaway AI spend per project / per user. | G21: Per-project token + $ cap; alert at 80%; hard block at 100%. | H21: MVP | I21: P0 | J21: S | K21: AI-01 | L21: Brendan | M21: Not Started
C22: CAT-01 | D22: Catalog | E22: Seeded default catalog (~300 items, 6 trades) | F22: Default library: carpentry, drywall, paint, electrical-rough, plumbing-rough, demo. | G22: JSON seed loads on first signup; user can override defaults. | H22: MVP | I22: P0 | J22: M | L22: Brendan | M22: Not Started | N22: Curate from public sources for prototype.
C23: CAT-02 | D23: Catalog | E23: Custom catalog items | F23: Add / edit user-specific catalog items. | G23: Per-workspace catalog table; full CRUD. | H23: MVP | I23: P0 | J23: S | K23: CAT-01 | L23: Brendan | M23: Not Started
C24: CAT-03 | D24: Catalog | E24: Save project as template | F24: Reuse a project's structure for the next similar bid. | G24: Stored as JSON; instantiate into new project preserving sections + items. | H24: MVP | I24: P0 | J24: M | K24: EST-02 | L24: Brendan | M24: Not Started
C25: MAT-01 | D25: Materials | E25: Material list per project | F25: Auto-derive a consolidated shopping list from line items; editable; exportable as PDF. | G25: Shows item, qty, unit, store hint, est cost; PDF export; shareable read-only link. | H25: MVP | I25: P0 | J25: M | K25: EST-02 | L25: Brendan | M25: Not Started | N25: MOVED from Phase 2. Truck-day shopping use-case.
C26: PROP-01 | D26: Proposals | E26: Proposal builder | F26: Compose cover letter, scope narrative, exclusions, payment schedule, timeline. | G26: Section editor with live preview; reorder; drafts auto-saved. | H26: MVP | I26: P0 | J26: M | K26: EST-03 | L26: Brendan | M26: Not Started
C27: PROP-02 | D27: Proposals | E27: Branded PDF | F27: PDF reflects contractor logo + brand color. | G27: React PDF render; matches preview within 5%; A4 + Letter sizes. | H27: MVP | I27: P0 | J27: M | K27: PROP-01 | L27: Brendan | M27: Not Started | N27: @react-pdf/renderer
C28: PROP-03 | D28: Proposals | E28: Email proposal to client | F28: Send PDF link via email to client. | G28: Resend send; tracking pixel for 'viewed'; link to download PDF. | H28: MVP | I28: P0 | J28: S | K28: PROP-02 | L28: Brendan | M28: Not Started | N28: MVP path: client signs paper or replies 'approved'. Hosted signing is Phase 2.
C29: SIGN-01 | D29: E-Sign | E29: Hosted client signing page | F29: Public token URL; client signs typed/drawn on canvas. | G29: Mobile-friendly; canvas signature; prevents replay; expires. | H29: Phase 2 | I29: P1 | J29: M | K29: PROP-03 | L29: Brendan | M29: Not Started | N29: MOVED from MVP per scope decision.
C30: SIGN-02 | D30: E-Sign | E30: Audit log on signature | F30: Capture IP, UA, timestamp, hash on every signature. | G30: Immutable audit row; shown on proposal detail page. | H30: Phase 2 | I30: P1 | J30: S | K30: SIGN-01 | L30: Brendan | M30: Not Started
C31: INFRA-01 | D31: Infrastructure | E31: Sentry + in-app feedback button | F31: Centralized error monitoring + an in-app 'Send feedback' button → Slack/Discord webhook. | G31: Errors captured with userId; feedback button on every screen. | H31: Phase 2 | I31: P1 | J31: S | L31: Brendan | M31: Not Started | N31: MOVED from MVP per scope decision.
C32: MAT-02 | D32: Materials | E32: Supplier prices | F32: Per-supplier price overrides for catalog items. | G32: Supplier table + price-list; price chosen at PO time. | H32: Phase 2 | I32: P1 | J32: M | K32: MAT-01 | L32: Brendan | M32: Not Started
C33: MAT-03 | D33: Materials | E33: PO PDF generation | F33: Generate purchase order PDF for a supplier. | G33: Filtered by supplier; PDF email-able; PO number sequence per workspace. | H33: Phase 2 | I33: P1 | J33: M | K33: MAT-02 | L33: Brendan | M33: Not Started
C34: REC-01 | D34: Receipts | E34: Capture receipt photo / PDF | F34: Snap or upload a paper receipt against a project. | G34: Stored with thumbnail; supports HEIC/PNG/JPG/PDF. | H34: Phase 2 | I34: P1 | J34: S | K34: PROJ-01 | L34: Brendan | M34: Not Started
C35: REC-02 | D35: Receipts | E35: Email-forward inbox for order confirmations | F35: Forward order-confirmation emails (HD / Lowe's / Menard's / Ace / Amazon) to a unique inbox. | G35: receipts+userid@app.com ingests; attachment + body stored against user. | H35: Phase 2 | I35: P1 | J35: M | L35: Brendan | M35: Not Started | N35: Postmark inbound or SendGrid Inbound Parse; SPF/DKIM verified.
C36: REC-03 | D36: Receipts | E36: OCR + GPT-4o vision parse | F36: Extract store, date, items, qty, unit price, tax, total from receipt or email. | G36: ≥85% field accuracy on test set of 30 receipts; structured JSON output. | H36: Phase 2 | I36: P1 | J36: L | K36: REC-01, REC-02 | L36: Brendan | M36: Not Started
C37: REC-04 | D37: Receipts | E37: Match receipt to project | F37: User picks project; AI suggests based on date/amount/store. | G37: Manual + AI-suggested match; one-click confirm. | H37: Phase 2 | I37: P1 | J37: M | K37: REC-03 | L37: Brendan | M37: Not Started
C38: REC-05 | D38: Receipts | E38: Reconcile actual vs. estimated materials | F38: Per line item, compare estimated vs. actual material spend. | G38: Variance %, overrun flag, drill-down to receipt. | H38: Phase 2 | I38: P1 | J38: M | K38: REC-04, MAT-01 | L38: Brendan | M38: Not Started
C39: REC-06 | D39: Receipts | E39: Export receipts by project | F39: ZIP of all receipts + summary CSV for tax/job-costing. | G39: Download endpoint; filterable by date range. | H39: Phase 2 | I39: P1 | J39: S | K39: REC-03 | L39: Brendan | M39: Not Started
C40: SCHED-01 | D40: Scheduling | E40: Project calendar | F40: Calendar view per project (day / week / month). | G40: Drag-create events; recurring events supported. | H40: Phase 2 | I40: P1 | J40: M | K40: PROJ-01 | L40: Brendan | M40: Not Started
C41: SCHED-02 | D41: Scheduling | E41: Sub assignments | F41: Assign subcontractors to scheduled tasks. | G41: Sub directory; assignment CRUD; conflict warnings. | H41: Phase 2 | I41: P1 | J41: M | K41: SCHED-01 | L41: Brendan | M41: Not Started
C42: SCHED-03 | D42: Scheduling | E42: SMS / email reminders to subs | F42: Notify subs day-before and morning-of an assignment. | G42: Twilio + Resend; opt-out link; delivery status tracked. | H42: Phase 2 | I42: P1 | J42: M | K42: SCHED-02 | L42: Brendan | M42: Not Started
C43: TIME-01 | D43: Time | E43: Crew clock-in / out | F43: Mobile clock-in to a project for crew members. | G43: GPS optional; manual entry fallback; geofence warning. | H43: Phase 2 | I43: P1 | J43: M | K43: PROJ-01 | L43: Brendan | M43: Not Started
C44: TIME-02 | D44: Time | E44: Hours roll-up to project actuals | F44: Compare estimated labor vs. actual hours per section. | G44: Per-section variance dashboard. | H44: Phase 2 | I44: P1 | J44: S | K44: TIME-01, EST-02 | L44: Brendan | M44: Not Started
C45: INV-01 | D45: Invoicing | E45: Convert proposal → invoice | F45: Convert a signed proposal into an invoice. | G45: Carries scope; editable; status tracking (draft/sent/paid). | H45: Phase 2 | I45: P1 | J45: M | K45: SIGN-01 | L45: Brendan | M45: Not Started
C46: INV-02 | D46: Invoicing | E46: Progress billing (draws) | F46: Configure draw schedule (deposit / mid / final). | G46: Per-draw invoices; auto-suggest based on milestones. | H46: Phase 2 | I46: P1 | J46: M | K46: INV-01 | L46: Brendan | M46: Not Started
C47: INV-03 | D47: Invoicing | E47: Payment link | F47: Generic 'pay link' placeholder; payment recorded against invoice. | G47: Manual mark-paid in Phase 2; Stripe integration deferred to Phase 4. | H47: Phase 2 | I47: P1 | J47: M | K47: INV-01 | L47: Brendan | M47: Not Started
... C49: CO-02 | D49: Change Orders | E49: Re-sign flow for change orders | F49: Client re-signs change order via hosted page. | G49: Reuses SIGN-01 flow; appended to audit log. | H49: Phase 2 | I49: P1 | J49: S | K49: CO-01, SIGN-01 | L49: Brendan | M49: Not Started
C50: TAX-01 | D50: 1099/Tax | E50: Subcontractor profile + W-9 capture | F50: Capture sub profile and W-9 PDF; encrypt EIN/SSN at rest. | G50: pgcrypto encryption; access logged; W-9 PDF stored. | H50: Phase 2 | I50: P1 | J50: M | L50: Brendan | M50: Not Started | N50: PII handling — review with privacy/legal before go-live.
C51: TAX-02 | D51: 1099/Tax | E51: Payment ledger by sub by year | F51: Track all payments to each sub by tax year. | G51: Per-sub annual total; filterable by year and project. | H51: Phase 2 | I51: P1 | J51: M | K51: TAX-01 | L51: Brendan | M51: Not Started
C52: TAX-03 | D52: 1099/Tax | E52: Generate 1099-NEC PDF | F52: Render IRS-aligned 1099-NEC PDF per sub (Copies B / C / 2). | G52: Matches IRS form layout; spot-check against IRS sample. | H52: Phase 2 | I52: P1 | J52: L | K52: TAX-02 | L52: Brendan | M52: Not Started | N52: Copy A requires IRS red-ink scannable form — direct user to e-file via IRS FIRE or Track1099 instead.
C53: TAX-04 | D53: 1099/Tax | E53: Year-end bulk packet | F53: ZIP of all subs' 1099s + summary CSV for the tax year. | G53: One-click export; idempotent (regeneratable). | H53: Phase 2 | I53: P1 | J53: S | K53: TAX-03 | L53: Brendan | M53: Not Started
C54: TAX-05 | D54: 1099/Tax | E54: 1096 transmittal generation | F54: Generate IRS Form 1096 if user paper-files. | G54: PDF; matches IRS form layout. | H54: Phase 2 | I54: P1 | J54: S | K54: TAX-03 | L54: Brendan | M54: Not Started
C55: COMM-01 | D55: Client | E55: Client portal (view-only) | F55: Client sees proposal, change orders, invoices in one URL. | G55: Token-gated; no login required for client. | H55: Phase 2 | I55: P1 | J55: M | K55: PROP-03 | L55: Brendan | M55: Not Started
C56: COMM-02 | D56: Client | E56: Comments on proposal sections | F56: Client and contractor can thread comments per section. | G56: Polling-based realtime OK; email notification on new comment. | H56: Phase 2 | I56: P1 | J56: M | K56: COMM-01 | L56: Brendan | M56: Not Started
C57: VIZ-01 | D57: Visualization | E57: 3D room scan | F57: Capture 3D geometry of an existing room. | G57: LiDAR via WebXR on supported phones; 8–12 photo photogrammetry fallback; mesh stored. | H57: Phase 3 | I57: P2 | J57: XL | K57: PROJ-03 | L57: Brendan | M57: Not Started | N57: Opt-in; LiDAR availability uneven on non-Pro iPhones.
C58: VIZ-02 | D58: Visualization | E58: 3D viewer (web) | F58: Render scanned room in proposal; client rotates / zooms. | G58: three.js / react-three-fiber; loads <3s on mid-tier mobile. | H58: Phase 3 | I58: P2 | J58: L | K58: VIZ-01 | L58: Brendan | M58: Not Started
C59: VIZ-03 | D59: Visualization | E59: Annotate 3D model with line items | F59: Tag surfaces in the model with line items (this wall = drywall + paint). | G59: Per-surface tag list; bidirectional link to estimate. | H59: Phase 3 | I59: P2 | J59: L | K59: VIZ-02, EST-02 | L59: Brendan | M59: Not Started
C60: VIZ-04 | D60: Visualization | E60: Before-photo capture & alignment | F60: Store original 'before' photos with camera pose for later alignment. | G60: EXIF preserved; manual alignment helper in UI. | H60: Phase 3 | I60: P2 | J60: M | K60: PROJ-03 | L60: Brendan | M60: Not Started
C61: VIZ-05 | D61: Visualization | E61: AI-generated 'after' photo | F61: Generate a photorealistic 'after' image conditioned on before-photo + scope text. | G61: Mandatory watermark 'AI-generated visualization, not a guarantee'; cap regenerations per proposal. | H61: Phase 3 | I61: P2 | J61: XL | K61: VIZ-04, EST-02 | L61: Brendan | M61: Not Started | N61: Image-gen API cost ~$0.05–0.15/image; ToS disclaimer required.
C62: VIZ-06 | D62: Visualization | E62: Side-by-side before / after slider | F62: Drag-slider compare in proposal PDF + client view. | G62: Touch swipe on mobile; static side-by-side fallback in PDF. | H62: Phase 3 | I62: P2 | J62: M | K62: VIZ-05 | L62: Brendan | M62: Not Started
C63: QB-01 | D63: Integration | E63: QuickBooks Online sync | F63: 2-way sync invoices, bills, customers with QBO. | G63: OAuth flow; daily sync; conflict resolution. | H63: Phase 4 | I63: P3 | J63: XL | K63: INV-01 | L63: Brendan | M63: Not Started
C64: MULTI-01 | D64: Admin | E64: Team roles (admin / foreman / sub) | F64: Multi-user workspaces with role-based access control. | G64: RBAC across all routes; invitation flow. | H64: Phase 4 | I64: P3 | J64: L | K64: AUTH-02 | L64: Brendan | M64: Not Started
C65: LAUNCH-01 | D65: Launch | E65: Stripe billing | F65: Subscription plans + checkout + customer portal. | G65: Stripe Checkout; webhooks for plan changes. | H65: Phase 4 | I65: P3 | J65: M | L65: Brendan | M65: Not Started
C66: LAUNCH-02 | D66: Launch | E66: iOS App Store build | F66: Capacitor wrapper of PWA; submit to App Store. | G66: TestFlight beta; App Store review approved. | H66: Phase 4 | I66: P3 | J66: L | L66: Brendan | M66: Not Started
C67: LAUNCH-03 | D67: Launch | E67: Android Play Store build | F67: Capacitor wrapper; submit to Play Store. | G67: Internal track + production track approved. | H67: Phase 4 | I67: P3 | J67: L | L67: Brendan | M67: Not Started
C68: LAUNCH-04 | D68: Launch | E68: Marketing site | F68: Public landing + pricing + features + signup CTA. | G68: Next.js public route; SEO optimized. | H68: Phase 4 | I68: P3 | J68: M | L68: Brendan | M68: Not Started
C69: LAUNCH-05 | D69: Launch | E69: Help center / docs | F69: Self-serve help docs and onboarding guides. | G69: MDX or Notion-backed; searchable. | H69: Phase 4 | I69: P3 | J69: M | L69: Brendan | M69: Not Started
C70: LAUNCH-06 | D70: Launch | E70: Compliance hardening (SOC2-lite) | F70: Audit log, data export, account deletion, encryption review. | G70: Audit log endpoint, export endpoint, deletion job, encryption-at-rest verified. | H70: Phase 4 | I70: P3 | J70: L | L70: Brendan | M70: Not Started
C71: LAUNCH-07 | D71: Launch | E71: Multi-tenant security audit | F71: Pen-test for row-level isolation across tenants. | G71: External pen test report; remediation completed. | H71: Phase 4 | I71: P3 | J71: M | K71: MULTI-01 | L71: Brendan | M71: Not Started
C72: LAUNCH-08 | D72: Launch | E72: Onboarding wizard | F72: Self-serve guided first-project creation. | G72: <3 min from signup to first estimate created. | H72: Phase 4 | I72: P3 | J72: M | L72: Brendan | M72: Not Started
C73: AGT-01 | D73: Automation | E73: Material-buying agent + delivery tracking | F73: Autonomous agent purchases approved project materials from supported suppliers and tracks delivery status. | G73: Reads MAT-01 list; user approves cart; agent places order via supplier API or email-cart; delivery status (ordered/shipped/delivered) updates project timeline; exception alerts on backorder. | H73: Phase 4 | I73: P3 | J73: XL | K73: MAT-01, MAT-02, REC-02 | L73: Brendan | M73: Not Started | N73: Start with one supplier (Home Depot Pro) before generalizing. Requires user-stored payment + delivery address.
C74: AGT-02 | D74: Automation | E74: Bid-send + follow-up agent | F74: Autonomous agent sends proposals to clients and follows up on a configurable cadence until accepted/declined. | G74: User approves send + cadence (e.g., D+3, D+7, D+14); agent emails follow-ups; stops on client reply, sign, or decline; weekly digest of open bids to contractor. | H74: Phase 4 | I74: P3 | J74: L | K74: PROP-03, SIGN-01 | L74: Brendan | M74: Not Started | N74: Drafts must be human-approved before initial send; follow-ups can be auto-approved.
C75: AGT-03 | D75: Automation | E75: Sub-estimate request agent | F75: Autonomous agent reaches out to selected subcontractors for trade estimates (e.g., electrical, plumbing) on a project. | G75: User picks trade + subs from directory; agent emails scope packet from estimate; collects responses (email or form); presents side-by-side comparison; nudges non-responders. | H75: Phase 4 | I75: P3 | J75: L | K75: SCHED-02, EST-02 | L75: Brendan | M75: Not Started | N75: Sub directory is a precondition; consider rate-limit + opt-out per sub.
C76: CAT-04 | D76: Catalog | E76: Shared catalog across users (backlog) | F76: Optional: contributors share + improve a community catalog; per-user overrides preserved. | G76: Opt-in; community items flagged; user can fork to private; contributor attribution. | H76: Phase 4 | I76: P3 | J76: L | K76: CAT-01, CAT-02 | L76: Brendan | M76: Not Started | N76: Backlog item per scope decision: prototype stays isolated. Revisit only if friend feedback asks for it.

Sheet A-Specific
C1: =MID(CELL("filename",A1),FIND("[",CELL("filename",A1))+1,FIND("]",CELL("filename",A1))-FIND("[",CELL("filename",A1))-1)&" - "&MID(CELL("filename",A1),FIND("]",CELL("filename",A1))+1,255)
A3: =IF(TRUE,"OK","ERROR") | C3: A-Specific — Picklists & Constants
C7: Phase | D7: Priority | E7: Status | F7: Effort | G7: Effort_Pts | H7: Category
C8: MVP | D8: P0 | E8: Not Started | F8: S | G8: 1 | H8: Auth
C9: Phase 2 | D9: P1 | E9: In Progress | F9: M | G9: 3 | H9: Projects
C10: Phase 3 | D10: P2 | E10: In Review | F10: L | G10: 7 | H10: Estimation
C11: Phase 4 | D11: P3 | E11: Done | F11: XL | G11: 12 | H11: AI Capture
E12: Deferred | H12: Catalog
H13: Materials
H14: Receipts
H15: Proposals
H16: E-Sign
H17: Scheduling
H18: Time
H19: Invoicing
H20: Change Orders
H21: 1099/Tax
H22: Client
H23: Visualization
H24: Integration
... H28: Automation

Sheet Z-Validation-Checks
C1: =MID(CELL("filename",A1),FIND("[",CELL("filename",A1))+1,FIND("]",CELL("filename",A1))-FIND("[",CELL("filename",A1))-1)&" - "&MID(CELL("filename",A1),FIND("]",CELL("filename",A1))+1,255)
A3: =IF(COUNTIF(D8:D20,"FAIL")=0,"OK","ERROR") | C3: Z-Validation-Checks — Workbook Integrity
C7: # | D7: Check | E7: Result | F7: Detail
C8: 1 | D8: All Feature_IDs are unique | E8: =IF(SUMPRODUCT((COUNTIF('I-Features'!$C$8:$C$76,'I-Features'!$C$8:$C$76)>1)*1)=0,"PASS","FAIL") | F8: =SUMPRODUCT((COUNTIF('I-Features'!$C$8:$C$76,'I-Features'!$C$8:$C$76)>1)*1)&" duplicate ID(s) detected"
C9: 2 | D9: All Phase values are valid | E9: =IF(SUMPRODUCT((COUNTIF('A-Specific'!$C$8:$C$11,'I-Features'!$H$8:$H$76)=0)*1)=0,"PASS","FAIL") | F9: =SUMPRODUCT((COUNTIF('A-Specific'!$C$8:$C$11,'I-Features'!$H$8:$H$76)=0)*1)&" invalid phase value(s)"
C10: 3 | D10: All Priority values are valid | E10: =IF(SUMPRODUCT((COUNTIF('A-Specific'!$D$8:$D$11,'I-Features'!$I$8:$I$76)=0)*1)=0,"PASS","FAIL") | F10: =SUMPRODUCT((COUNTIF('A-Specific'!$D$8:$D$11,'I-Features'!$I$8:$I$76)=0)*1)&" invalid priority value(s)"
C11: 4 | D11: All Effort values are valid | E11: =IF(SUMPRODUCT((COUNTIF('A-Specific'!$F$8:$F$11,'I-Features'!$J$8:$J$76)=0)*1)=0,"PASS","FAIL") | F11: =SUMPRODUCT((COUNTIF('A-Specific'!$F$8:$F$11,'I-Features'!$J$8:$J$76)=0)*1)&" invalid effort value(s)"
C12: 5 | D12: All Status values are valid | E12: =IF(SUMPRODUCT((COUNTIF('A-Specific'!$E$8:$E$12,'I-Features'!$M$8:$M$76)=0)*1)=0,"PASS","FAIL") | F12: =SUMPRODUCT((COUNTIF('A-Specific'!$E$8:$E$12,'I-Features'!$M$8:$M$76)=0)*1)&" invalid status value(s)"
C13: 6 | D13: Total feature count = 69 | E13: =IF(COUNTA('I-Features'!$C$8:$C$76)=69,"PASS","FAIL") | F13: ="Found "&COUNTA('I-Features'!$C$8:$C$76)&" features (expected 69)"
C14: 7 | D14: MVP feature count = 21 | E14: =IF(COUNTIF('I-Features'!$H$8:$H$76,"MVP")=21,"PASS","FAIL") | F14: ="Found "&COUNTIF('I-Features'!$H$8:$H$76,"MVP")&" MVP features (expected 21)"
C15: 8 | D15: Phase 2 feature count = 28 | E15: =IF(COUNTIF('I-Features'!$H$8:$H$76,"Phase 2")=28,"PASS","FAIL") | F15: ="Found "&COUNTIF('I-Features'!$H$8:$H$76,"Phase 2")&" Phase 2 features (expected 28)"
C16: 9 | D16: Phase 3 feature count = 6 | E16: =IF(COUNTIF('I-Features'!$H$8:$H$76,"Phase 3")=6,"PASS","FAIL") | F16: ="Found "&COUNTIF('I-Features'!$H$8:$H$76,"Phase 3")&" Phase 3 features (expected 6)"
C17: 10 | D17: Phase 4 feature count = 14 | E17: =IF(COUNTIF('I-Features'!$H$8:$H$76,"Phase 4")=14,"PASS","FAIL") | F17: ="Found "&COUNTIF('I-Features'!$H$8:$H$76,"Phase 4")&" Phase 4 features (expected 14)"
